LICENSE.txt
setup.cfg
setup.py
testGZ/Package.py
testGZ/__init__.py
testGZ.egg-info/PKG-INFO
testGZ.egg-info/SOURCES.txt
testGZ.egg-info/dependency_links.txt
testGZ.egg-info/requires.txt
testGZ.egg-info/top_level.txt
testGZ/IMAGES/100008.jpg
testGZ/IMAGES/100023.jpg
testGZ/IMAGES/100053.jpg
testGZ/IMAGES/100078.jpg
testGZ/IMAGES/100090.jpg
testGZ/IMAGES/100122.jpg
testGZ/IMAGES/100123.jpg
testGZ/IMAGES/100128.jpg
testGZ/IMAGES/100134.jpg
testGZ/IMAGES/100143.jpg
testGZ/IMAGES/100150.jpg
testGZ/IMAGES/100157.jpg
testGZ/IMAGES/100204.jpg
testGZ/IMAGES/100237.jpg
testGZ/IMAGES/100259.jpg
testGZ/IMAGES/100263.jpg
testGZ/IMAGES/100288.jpg
testGZ/IMAGES/100295.jpg
testGZ/IMAGES/100322.jpg
testGZ/IMAGES/100335.jpg
testGZ/IMAGES/100380.jpg
testGZ/IMAGES/100382.jpg
testGZ/IMAGES/100383.jpg
testGZ/IMAGES/100402.jpg
testGZ/IMAGES/100428.jpg
testGZ/IMAGES/100434.jpg
testGZ/IMAGES/100444.jpg
testGZ/IMAGES/100445.jpg
testGZ/IMAGES/100458.jpg
testGZ/IMAGES/100474.jpg
testGZ/IMAGES/100479.jpg
testGZ/IMAGES/100506.jpg
testGZ/IMAGES/100513.jpg
testGZ/IMAGES/100520.jpg
testGZ/IMAGES/100541.jpg
testGZ/IMAGES/100561.jpg
testGZ/IMAGES/100571.jpg
testGZ/IMAGES/100601.jpg
testGZ/IMAGES/100623.jpg
testGZ/IMAGES/100672.jpg
testGZ/IMAGES/100673.jpg
testGZ/IMAGES/100724.jpg
testGZ/IMAGES/100727.jpg
testGZ/IMAGES/100730.jpg
testGZ/IMAGES/100740.jpg
testGZ/IMAGES/100744.jpg
testGZ/IMAGES/100765.jpg
testGZ/IMAGES/100774.jpg
testGZ/IMAGES/100801.jpg
testGZ/IMAGES/100813.jpg
testGZ/IMAGES/100821.jpg
testGZ/IMAGES/100822.jpg
testGZ/IMAGES/100836.jpg
testGZ/IMAGES/100852.jpg
testGZ/IMAGES/100859.jpg
testGZ/IMAGES/100861.jpg
testGZ/IMAGES/100867.jpg
testGZ/IMAGES/100887.jpg
testGZ/IMAGES/100894.jpg
testGZ/IMAGES/100938.jpg
testGZ/IMAGES/100951.jpg
testGZ/IMAGES/100986.jpg
testGZ/IMAGES/101007.jpg
testGZ/IMAGES/101061.jpg
testGZ/IMAGES/101074.jpg
testGZ/IMAGES/101092.jpg
testGZ/IMAGES/101127.jpg
testGZ/IMAGES/101133.jpg
testGZ/IMAGES/101135.jpg
testGZ/IMAGES/101140.jpg
testGZ/IMAGES/101151.jpg
testGZ/IMAGES/101164.jpg
testGZ/IMAGES/101166.jpg
testGZ/IMAGES/101181.jpg
testGZ/IMAGES/101232.jpg
testGZ/IMAGES/101239.jpg
testGZ/IMAGES/101244.jpg
